{
  "data": [
    {
      "id": 2,
      "documentId": "qu7kkivxka4l7y94rfxx356f",
      "name": "postres"
    },
    {
      "id": 4,
      "documentId": "rfefbs4hcmysymot6okj6zdy",
      "name": "cupcakes"
    },
    {
      "id": 6,
      "documentId": "xyelsp63jrgaeu487vl720l5",
      "name": "tortas"
    },
    {
      "id": 9,
      "documentId": "rf9ej9l7ydqxg0btp60m03j2",
      "name": "galletas"
    },
    {
      "id": 13,
      "documentId": "crmix4tdq01r6omjlsrwurcd",
      "name": "personalized"
    }
  ]
}

